README.md
setup.py
libsignal/__init__.py
libsignal/axolotladdress.py
libsignal/duplicatemessagexception.py
libsignal/identitykey.py
libsignal/identitykeypair.py
libsignal/invalidkeyexception.py
libsignal/invalidkeyidexception.py
libsignal/invalidmessageexception.py
libsignal/invalidversionexception.py
libsignal/legacymessageexception.py
libsignal/nosessionexception.py
libsignal/sessionbuilder.py
libsignal/sessioncipher.py
libsignal/statekeyexchangeexception.py
libsignal/untrustedidentityexception.py
libsignal.egg-info/PKG-INFO
libsignal.egg-info/SOURCES.txt
libsignal.egg-info/dependency_links.txt
libsignal.egg-info/requires.txt
libsignal.egg-info/top_level.txt
libsignal/ecc/__init__.py
libsignal/ecc/curve.py
libsignal/ecc/djbec.py
libsignal/ecc/ec.py
libsignal/ecc/eckeypair.py
libsignal/groups/__init__.py
libsignal/groups/groupcipher.py
libsignal/groups/groupsessionbuilder.py
libsignal/groups/senderkeyname.py
libsignal/groups/ratchet/__init__.py
libsignal/groups/ratchet/senderchainkey.py
libsignal/groups/ratchet/sendermessagekey.py
libsignal/groups/state/__init__.py
libsignal/groups/state/senderkeyrecord.py
libsignal/groups/state/senderkeystate.py
libsignal/groups/state/senderkeystore.py
libsignal/kdf/__init__.py
libsignal/kdf/derivedmessagesecrets.py
libsignal/kdf/derivedrootsecrets.py
libsignal/kdf/hkdf.py
libsignal/kdf/hkdfv2.py
libsignal/kdf/hkdfv3.py
libsignal/kdf/messagekeys.py
libsignal/protocol/__init__.py
libsignal/protocol/ciphertextmessage.py
libsignal/protocol/keyexchangemessage.py
libsignal/protocol/prekeywhispermessage.py
libsignal/protocol/senderkeydistributionmessage.py
libsignal/protocol/senderkeymessage.py
libsignal/protocol/whispermessage.py
libsignal/protocol/whisperprotos_pb2.py
libsignal/ratchet/__init__.py
libsignal/ratchet/aliceaxolotlparameters.py
libsignal/ratchet/bobaxolotlparamaters.py
libsignal/ratchet/chainkey.py
libsignal/ratchet/ratchetingsession.py
libsignal/ratchet/rootkey.py
libsignal/ratchet/symmetricaxolotlparameters.py
libsignal/state/__init__.py
libsignal/state/axolotlstore.py
libsignal/state/identitykeystore.py
libsignal/state/prekeybundle.py
libsignal/state/prekeyrecord.py
