Metadata-Version: 2.1
Name: libsignal
Version: 0.0.3
Summary: Python port of libsignal-protocol-java
Home-page: https://github.com/ForstaLabs/libsignal-python
License: GPLv3 License
Platform: any
Classifier: Development Status :: 5 - Production/Stable
Classifier: Intended Audience :: Developers
Classifier: License :: OSI Approved :: GNU General Public License v3 (GPLv3)
Classifier: Natural Language :: English
Classifier: Programming Language :: Python :: 3.6
Classifier: Programming Language :: Python :: 3.7
Classifier: Topic :: Security :: Cryptography
Classifier: Topic :: Software Development :: Libraries :: Python Modules
